Workbook

Sheet Dashboard
A1: 88gravity | Task Dashboard
A3: Total Tasks | C3: Overdue | E3: Due Today | G3: In Progress | I3: Pending | K3: Not Started | M3: Done
A4: =COUNTA('Task Tracker'!C3:C202) -> 20 | C4: =COUNTIF('Task Tracker'!I3:I202,"Overdue") -> 2 | E4: =COUNTIFS('Task Tracker'!G3:G202,TODAY(),'Task Tracker'!I3:I202,"<>Done") -> 2 | G4: =COUNTIF('Task Tracker'!I3:I202,"In Progress") -> 6 | I4: =COUNTIF('Task Tracker'!I3:I202,"Pending") -> 6 | K4: =COUNTIF('Task Tracker'!I3:I202,"Not Started") -> 6 | M4: =COUNTIF('Task Tracker'!I3:I202,"Done") -> 0
A7: View by Client / Project
A8: Name | B8: Overdue | C8: In Progress | D8: Pending | E8: Not Started | F8: Done | G8: Total
A9: Enout | B9: =COUNTIFS('Task Tracker'!E3:E202,"Enout",'Task Tracker'!I3:I202,"Overdue") -> 0 | C9: =COUNTIFS('Task Tracker'!E3:E202,"Enout",'Task Tracker'!I3:I202,"In Progress") -> 0 | D9: =COUNTIFS('Task Tracker'!E3:E202,"Enout",'Task Tracker'!I3:I202,"Pending") -> 2 | E9: =COUNTIFS('Task Tracker'!E3:E202,"Enout",'Task Tracker'!I3:I202,"Not Started") -> 0 | F9: =COUNTIFS('Task Tracker'!E3:E202,"Enout",'Task Tracker'!I3:I202,"Done") -> 0 | G9: =COUNTIF('Task Tracker'!E3:E202,"Enout") -> 2
A10: Tiaraa Kerala | B10: =COUNTIFS('Task Tracker'!E3:E202,"Tiaraa Kerala",'Task Tracker'!I3:I202,"Overdue") -> 0 | C10: =COUNTIFS('Task Tracker'!E3:E202,"Tiaraa Kerala",'Task Tracker'!I3:I202,"In Progress") -> 1 | D10: =COUNTIFS('Task Tracker'!E3:E202,"Tiaraa Kerala",'Task Tracker'!I3:I202,"Pending") -> 0 | E10: =COUNTIFS('Task Tracker'!E3:E202,"Tiaraa Kerala",'Task Tracker'!I3:I202,"Not Started") -> 0 | F10: =COUNTIFS('Task Tracker'!E3:E202,"Tiaraa Kerala",'Task Tracker'!I3:I202,"Done") -> 0 | G10: =COUNTIF('Task Tracker'!E3:E202,"Tiaraa Kerala") -> 1
A11: Tiaraq Hotels | B11: =COUNTIFS('Task Tracker'!E3:E202,"Tiaraq Hotels",'Task Tracker'!I3:I202,"Overdue") -> 0 | C11: =COUNTIFS('Task Tracker'!E3:E202,"Tiaraq Hotels",'Task Tracker'!I3:I202,"In Progress") -> 0 | D11: =COUNTIFS('Task Tracker'!E3:E202,"Tiaraq Hotels",'Task Tracker'!I3:I202,"Pending") -> 0 | E11: =COUNTIFS('Task Tracker'!E3:E202,"Tiaraq Hotels",'Task Tracker'!I3:I202,"Not Started") -> 1 | F11: =COUNTIFS('Task Tracker'!E3:E202,"Tiaraq Hotels",'Task Tracker'!I3:I202,"Done") -> 0 | G11: =COUNTIF('Task Tracker'!E3:E202,"Tiaraq Hotels") -> 1
A12: Colonelz | B12: =COUNTIFS('Task Tracker'!E3:E202,"Colonelz",'Task Tracker'!I3:I202,"Overdue") -> 1 | C12: =COUNTIFS('Task Tracker'!E3:E202,"Colonelz",'Task Tracker'!I3:I202,"In Progress") -> 0 | D12: =COUNTIFS('Task Tracker'!E3:E202,"Colonelz",'Task Tracker'!I3:I202,"Pending") -> 1 | E12: =COUNTIFS('Task Tracker'!E3:E202,"Colonelz",'Task Tracker'!I3:I202,"Not Started") -> 0 | F12: =COUNTIFS('Task Tracker'!E3:E202,"Colonelz",'Task Tracker'!I3:I202,"Done") -> 0 | G12: =COUNTIF('Task Tracker'!E3:E202,"Colonelz") -> 2
A13: Chalk Studio | B13: =COUNTIFS('Task Tracker'!E3:E202,"Chalk Studio",'Task Tracker'!I3:I202,"Overdue") -> 0 | C13: =COUNTIFS('Task Tracker'!E3:E202,"Chalk Studio",'Task Tracker'!I3:I202,"In Progress") -> 1 | D13: =COUNTIFS('Task Tracker'!E3:E202,"Chalk Studio",'Task Tracker'!I3:I202,"Pending") -> 0 | E13: =COUNTIFS('Task Tracker'!E3:E202,"Chalk Studio",'Task Tracker'!I3:I202,"Not Started") -> 0 | F13: =COUNTIFS('Task Tracker'!E3:E202,"Chalk Studio",'Task Tracker'!I3:I202,"Done") -> 0 | G13: =COUNTIF('Task Tracker'!E3:E202,"Chalk Studio") -> 1
A14: Catalyze | B14: =COUNTIFS('Task Tracker'!E3:E202,"Catalyze",'Task Tracker'!I3:I202,"Overdue") -> 1 | C14: =COUNTIFS('Task Tracker'!E3:E202,"Catalyze",'Task Tracker'!I3:I202,"In Progress") -> 1 | D14: =COUNTIFS('Task Tracker'!E3:E202,"Catalyze",'Task Tracker'!I3:I202,"Pending") -> 0 | E14: =COUNTIFS('Task Tracker'!E3:E202,"Catalyze",'Task Tracker'!I3:I202,"Not Started") -> 0 | F14: =COUNTIFS('Task Tracker'!E3:E202,"Catalyze",'Task Tracker'!I3:I202,"Done") -> 0 | G14: =COUNTIF('Task Tracker'!E3:E202,"Catalyze") -> 2
A15: Mobility Infotech | B15: =COUNTIFS('Task Tracker'!E3:E202,"Mobility Infotech",'Task Tracker'!I3:I202,"Overdue") -> 0 | C15: =COUNTIFS('Task Tracker'!E3:E202,"Mobility Infotech",'Task Tracker'!I3:I202,"In Progress") -> 1 | D15: =COUNTIFS('Task Tracker'!E3:E202,"Mobility Infotech",'Task Tracker'!I3:I202,"Pending") -> 0 | E15: =COUNTIFS('Task Tracker'!E3:E202,"Mobility Infotech",'Task Tracker'!I3:I202,"Not Started") -> 0 | F15: =COUNTIFS('Task Tracker'!E3:E202,"Mobility Infotech",'Task Tracker'!I3:I202,"Done") -> 0 | G15: =COUNTIF('Task Tracker'!E3:E202,"Mobility Infotech") -> 1
A16: SKIL Events | B16: =COUNTIFS('Task Tracker'!E3:E202,"SKIL Events",'Task Tracker'!I3:I202,"Overdue") -> 0 | C16: =COUNTIFS('Task Tracker'!E3:E202,"SKIL Events",'Task Tracker'!I3:I202,"In Progress") -> 0 | D16: =COUNTIFS('Task Tracker'!E3:E202,"SKIL Events",'Task Tracker'!I3:I202,"Pending") -> 0 | E16: =COUNTIFS('Task Tracker'!E3:E202,"SKIL Events",'Task Tracker'!I3:I202,"Not Started") -> 1 | F16: =COUNTIFS('Task Tracker'!E3:E202,"SKIL Events",'Task Tracker'!I3:I202,"Done") -> 0 | G16: =COUNTIF('Task Tracker'!E3:E202,"SKIL Events") -> 1
A17: Neon Cloud | B17: =COUNTIFS('Task Tracker'!E3:E202,"Neon Cloud",'Task Tracker'!I3:I202,"Overdue") -> 0 | C17: =COUNTIFS('Task Tracker'!E3:E202,"Neon Cloud",'Task Tracker'!I3:I202,"In Progress") -> 0 | D17: =COUNTIFS('Task Tracker'!E3:E202,"Neon Cloud",'Task Tracker'!I3:I202,"Pending") -> 1 | E17: =COUNTIFS('Task Tracker'!E3:E202,"Neon Cloud",'Task Tracker'!I3:I202,"Not Started") -> 0 | F17: =COUNTIFS('Task Tracker'!E3:E202,"Neon Cloud",'Task Tracker'!I3:I202,"Done") -> 0 | G17: =COUNTIF('Task Tracker'!E3:E202,"Neon Cloud") -> 1
A18: B2B Prospect | B18: =COUNTIFS('Task Tracker'!E3:E202,"B2B Prospect",'Task Tracker'!I3:I202,"Overdue") -> 0 | C18: =COUNTIFS('Task Tracker'!E3:E202,"B2B Prospect",'Task Tracker'!I3:I202,"In Progress") -> 0 | D18: =COUNTIFS('Task Tracker'!E3:E202,"B2B Prospect",'Task Tracker'!I3:I202,"Pending") -> 1 | E18: =COUNTIFS('Task Tracker'!E3:E202,"B2B Prospect",'Task Tracker'!I3:I202,"Not Started") -> 0 | F18: =COUNTIFS('Task Tracker'!E3:E202,"B2B Prospect",'Task Tracker'!I3:I202,"Done") -> 0 | G18: =COUNTIF('Task Tracker'!E3:E202,"B2B Prospect") -> 1
A19: Prospect | B19: =COUNTIFS('Task Tracker'!E3:E202,"Prospect",'Task Tracker'!I3:I202,"Overdue") -> 0 | C19: =COUNTIFS('Task Tracker'!E3:E202,"Prospect",'Task Tracker'!I3:I202,"In Progress") -> 0 | D19: =COUNTIFS('Task Tracker'!E3:E202,"Prospect",'Task Tracker'!I3:I202,"Pending") -> 0 | E19: =COUNTIFS('Task Tracker'!E3:E202,"Prospect",'Task Tracker'!I3:I202,"Not Started") -> 1 | F19: =COUNTIFS('Task Tracker'!E3:E202,"Prospect",'Task Tracker'!I3:I202,"Done") -> 0 | G19: =COUNTIF('Task Tracker'!E3:E202,"Prospect") -> 1
A20: Internal | B20: =COUNTIFS('Task Tracker'!E3:E202,"Internal",'Task Tracker'!I3:I202,"Overdue") -> 0 | C20: =COUNTIFS('Task Tracker'!E3:E202,"Internal",'Task Tracker'!I3:I202,"In Progress") -> 2 | D20: =COUNTIFS('Task Tracker'!E3:E202,"Internal",'Task Tracker'!I3:I202,"Pending") -> 1 | E20: =COUNTIFS('Task Tracker'!E3:E202,"Internal",'Task Tracker'!I3:I202,"Not Started") -> 3 | F20: =COUNTIFS('Task Tracker'!E3:E202,"Internal",'Task Tracker'!I3:I202,"Done") -> 0 | G20: =COUNTIF('Task Tracker'!E3:E202,"Internal") -> 6
A23: View by Assignee
A24: Name | B24: Overdue | C24: In Progress | D24: Pending | E24: Not Started | F24: Done | G24: Total
A25: Adarsh | B25: =COUNTIFS('Task Tracker'!D3:D202,"Adarsh",'Task Tracker'!I3:I202,"Overdue") -> 2 | C25: =COUNTIFS('Task Tracker'!D3:D202,"Adarsh",'Task Tracker'!I3:I202,"In Progress") -> 0 | D25: =COUNTIFS('Task Tracker'!D3:D202,"Adarsh",'Task Tracker'!I3:I202,"Pending") -> 4 | E25: =COUNTIFS('Task Tracker'!D3:D202,"Adarsh",'Task Tracker'!I3:I202,"Not Started") -> 0 | F25: =COUNTIFS('Task Tracker'!D3:D202,"Adarsh",'Task Tracker'!I3:I202,"Done") -> 0 | G25: =COUNTIF('Task Tracker'!D3:D202,"Adarsh") -> 6
A26: Kuldeep | B26: =COUNTIFS('Task Tracker'!D3:D202,"Kuldeep",'Task Tracker'!I3:I202,"Overdue") -> 0 | C26: =COUNTIFS('Task Tracker'!D3:D202,"Kuldeep",'Task Tracker'!I3:I202,"In Progress") -> 0 | D26: =COUNTIFS('Task Tracker'!D3:D202,"Kuldeep",'Task Tracker'!I3:I202,"Pending") -> 0 | E26: =COUNTIFS('Task Tracker'!D3:D202,"Kuldeep",'Task Tracker'!I3:I202,"Not Started") -> 0 | F26: =COUNTIFS('Task Tracker'!D3:D202,"Kuldeep",'Task Tracker'!I3:I202,"Done") -> 0 | G26: =COUNTIF('Task Tracker'!D3:D202,"Kuldeep") -> 0
A27: Priya | B27: =COUNTIFS('Task Tracker'!D3:D202,"Priya",'Task Tracker'!I3:I202,"Overdue") -> 0 | C27: =COUNTIFS('Task Tracker'!D3:D202,"Priya",'Task Tracker'!I3:I202,"In Progress") -> 1 | D27: =COUNTIFS('Task Tracker'!D3:D202,"Priya",'Task Tracker'!I3:I202,"Pending") -> 1 | E27: =COUNTIFS('Task Tracker'!D3:D202,"Priya",'Task Tracker'!I3:I202,"Not Started") -> 1 | F27: =COUNTIFS('Task Tracker'!D3:D202,"Priya",'Task Tracker'!I3:I202,"Done") -> 0 | G27: =COUNTIF('Task Tracker'!D3:D202,"Priya") -> 3
A28: Rahul | B28: =COUNTIFS('Task Tracker'!D3:D202,"Rahul",'Task Tracker'!I3:I202,"Overdue") -> 0 | C28: =COUNTIFS('Task Tracker'!D3:D202,"Rahul",'Task Tracker'!I3:I202,"In Progress") -> 2 | D28: =COUNTIFS('Task Tracker'!D3:D202,"Rahul",'Task Tracker'!I3:I202,"Pending") -> 0 | E28: =COUNTIFS('Task Tracker'!D3:D202,"Rahul",'Task Tracker'!I3:I202,"Not Started") -> 2 | F28: =COUNTIFS('Task Tracker'!D3:D202,"Rahul",'Task Tracker'!I3:I202,"Done") -> 0 | G28: =COUNTIF('Task Tracker'!D3:D202,"Rahul") -> 4
A29: SEO Team | B29: =COUNTIFS('Task Tracker'!D3:D202,"SEO Team",'Task Tracker'!I3:I202,"Overdue") -> 0 | C29: =COUNTIFS('Task Tracker'!D3:D202,"SEO Team",'Task Tracker'!I3:I202,"In Progress") -> 2 | D29: =COUNTIFS('Task Tracker'!D3:D202,"SEO Team",'Task Tracker'!I3:I202,"Pending") -> 0 | E29: =COUNTIFS('Task Tracker'!D3:D202,"SEO Team",'Task Tracker'!I3:I202,"Not Started") -> 1 | F29: =COUNTIFS('Task Tracker'!D3:D202,"SEO Team",'Task Tracker'!I3:I202,"Done") -> 0 | G29: =COUNTIF('Task Tracker'!D3:D202,"SEO Team") -> 3
A30: Content Team | B30: =COUNTIFS('Task Tracker'!D3:D202,"Content Team",'Task Tracker'!I3:I202,"Overdue") -> 0 | C30: =COUNTIFS('Task Tracker'!D3:D202,"Content Team",'Task Tracker'!I3:I202,"In Progress") -> 0 | D30: =COUNTIFS('Task Tracker'!D3:D202,"Content Team",'Task Tracker'!I3:I202,"Pending") -> 0 | E30: =COUNTIFS('Task Tracker'!D3:D202,"Content Team",'Task Tracker'!I3:I202,"Not Started") -> 1 | F30: =COUNTIFS('Task Tracker'!D3:D202,"Content Team",'Task Tracker'!I3:I202,"Done") -> 0 | G30: =COUNTIF('Task Tracker'!D3:D202,"Content Team") -> 1
A31: Sales Team | B31: =COUNTIFS('Task Tracker'!D3:D202,"Sales Team",'Task Tracker'!I3:I202,"Overdue") -> 0 | C31: =COUNTIFS('Task Tracker'!D3:D202,"Sales Team",'Task Tracker'!I3:I202,"In Progress") -> 0 | D31: =COUNTIFS('Task Tracker'!D3:D202,"Sales Team",'Task Tracker'!I3:I202,"Pending") -> 0 | E31: =COUNTIFS('Task Tracker'!D3:D202,"Sales Team",'Task Tracker'!I3:I202,"Not Started") -> 1 | F31: =COUNTIFS('Task Tracker'!D3:D202,"Sales Team",'Task Tracker'!I3:I202,"Done") -> 0 | G31: =COUNTIF('Task Tracker'!D3:D202,"Sales Team") -> 1
A32: Social Team | B32: =COUNTIFS('Task Tracker'!D3:D202,"Social Team",'Task Tracker'!I3:I202,"Overdue") -> 0 | C32: =COUNTIFS('Task Tracker'!D3:D202,"Social Team",'Task Tracker'!I3:I202,"In Progress") -> 1 | D32: =COUNTIFS('Task Tracker'!D3:D202,"Social Team",'Task Tracker'!I3:I202,"Pending") -> 0 | E32: =COUNTIFS('Task Tracker'!D3:D202,"Social Team",'Task Tracker'!I3:I202,"Not Started") -> 0 | F32: =COUNTIFS('Task Tracker'!D3:D202,"Social Team",'Task Tracker'!I3:I202,"Done") -> 0 | G32: =COUNTIF('Task Tracker'!D3:D202,"Social Team") -> 1
A33: Dev Team | B33: =COUNTIFS('Task Tracker'!D3:D202,"Dev Team",'Task Tracker'!I3:I202,"Overdue") -> 0 | C33: =COUNTIFS('Task Tracker'!D3:D202,"Dev Team",'Task Tracker'!I3:I202,"In Progress") -> 0 | D33: =COUNTIFS('Task Tracker'!D3:D202,"Dev Team",'Task Tracker'!I3:I202,"Pending") -> 1 | E33: =COUNTIFS('Task Tracker'!D3:D202,"Dev Team",'Task Tracker'!I3:I202,"Not Started") -> 0 | F33: =COUNTIFS('Task Tracker'!D3:D202,"Dev Team",'Task Tracker'!I3:I202,"Done") -> 0 | G33: =COUNTIF('Task Tracker'!D3:D202,"Dev Team") -> 1
A34: HR Team | B34: =COUNTIFS('Task Tracker'!D3:D202,"HR Team",'Task Tracker'!I3:I202,"Overdue") -> 0 | C34: =COUNTIFS('Task Tracker'!D3:D202,"HR Team",'Task Tracker'!I3:I202,"In Progress") -> 0 | D34: =COUNTIFS('Task Tracker'!D3:D202,"HR Team",'Task Tracker'!I3:I202,"Pending") -> 0 | E34: =COUNTIFS('Task Tracker'!D3:D202,"HR Team",'Task Tracker'!I3:I202,"Not Started") -> 0 | F34: =COUNTIFS('Task Tracker'!D3:D202,"HR Team",'Task Tracker'!I3:I202,"Done") -> 0 | G34: =COUNTIF('Task Tracker'!D3:D202,"HR Team") -> 0
A37: View by Department
A38: Name | B38: Overdue | C38: In Progress | D38: Pending | E38: Not Started | F38: Done | G38: Total
A39: Client | B39: =COUNTIFS('Task Tracker'!B3:B202,"Client",'Task Tracker'!I3:I202,"Overdue") -> 0 | C39: =COUNTIFS('Task Tracker'!B3:B202,"Client",'Task Tracker'!I3:I202,"In Progress") -> 3 | D39: =COUNTIFS('Task Tracker'!B3:B202,"Client",'Task Tracker'!I3:I202,"Pending") -> 3 | E39: =COUNTIFS('Task Tracker'!B3:B202,"Client",'Task Tracker'!I3:I202,"Not Started") -> 2 | F39: =COUNTIFS('Task Tracker'!B3:B202,"Client",'Task Tracker'!I3:I202,"Done") -> 0 | G39: =COUNTIF('Task Tracker'!B3:B202,"Client") -> 8
A40: Finance | B40: =COUNTIFS('Task Tracker'!B3:B202,"Finance",'Task Tracker'!I3:I202,"Overdue") -> 2 | C40: =COUNTIFS('Task Tracker'!B3:B202,"Finance",'Task Tracker'!I3:I202,"In Progress") -> 0 | D40: =COUNTIFS('Task Tracker'!B3:B202,"Finance",'Task Tracker'!I3:I202,"Pending") -> 0 | E40: =COUNTIFS('Task Tracker'!B3:B202,"Finance",'Task Tracker'!I3:I202,"Not Started") -> 0 | F40: =COUNTIFS('Task Tracker'!B3:B202,"Finance",'Task Tracker'!I3:I202,"Done") -> 0 | G40: =COUNTIF('Task Tracker'!B3:B202,"Finance") -> 2
A41: Sales | B41: =COUNTIFS('Task Tracker'!B3:B202,"Sales",'Task Tracker'!I3:I202,"Overdue") -> 0 | C41: =COUNTIFS('Task Tracker'!B3:B202,"Sales",'Task Tracker'!I3:I202,"In Progress") -> 0 | D41: =COUNTIFS('Task Tracker'!B3:B202,"Sales",'Task Tracker'!I3:I202,"Pending") -> 2 | E41: =COUNTIFS('Task Tracker'!B3:B202,"Sales",'Task Tracker'!I3:I202,"Not Started") -> 2 | F41: =COUNTIFS('Task Tracker'!B3:B202,"Sales",'Task Tracker'!I3:I202,"Done") -> 0 | G41: =COUNTIF('Task Tracker'!B3:B202,"Sales") -> 4
A42: HR | B42: =COUNTIFS('Task Tracker'!B3:B202,"HR",'Task Tracker'!I3:I202,"Overdue") -> 0 | C42: =COUNTIFS('Task Tracker'!B3:B202,"HR",'Task Tracker'!I3:I202,"In Progress") -> 2 | D42: =COUNTIFS('Task Tracker'!B3:B202,"HR",'Task Tracker'!I3:I202,"Pending") -> 0 | E42: =COUNTIFS('Task Tracker'!B3:B202,"HR",'Task Tracker'!I3:I202,"Not Started") -> 2 | F42: =COUNTIFS('Task Tracker'!B3:B202,"HR",'Task Tracker'!I3:I202,"Done") -> 0 | G42: =COUNTIF('Task Tracker'!B3:B202,"HR") -> 4
A43: Team | B43: =COUNTIFS('Task Tracker'!B3:B202,"Team",'Task Tracker'!I3:I202,"Overdue") -> 0 | C43: =COUNTIFS('Task Tracker'!B3:B202,"Team",'Task Tracker'!I3:I202,"In Progress") -> 1 | D43: =COUNTIFS('Task Tracker'!B3:B202,"Team",'Task Tracker'!I3:I202,"Pending") -> 1 | E43: =COUNTIFS('Task Tracker'!B3:B202,"Team",'Task Tracker'!I3:I202,"Not Started") -> 0 | F43: =COUNTIFS('Task Tracker'!B3:B202,"Team",'Task Tracker'!I3:I202,"Done") -> 0 | G43: =COUNTIF('Task Tracker'!B3:B202,"Team") -> 2
A44: Operations | B44: =COUNTIFS('Task Tracker'!B3:B202,"Operations",'Task Tracker'!I3:I202,"Overdue") -> 0 | C44: =COUNTIFS('Task Tracker'!B3:B202,"Operations",'Task Tracker'!I3:I202,"In Progress") -> 0 | D44: =COUNTIFS('Task Tracker'!B3:B202,"Operations",'Task Tracker'!I3:I202,"Pending") -> 0 | E44: =COUNTIFS('Task Tracker'!B3:B202,"Operations",'Task Tracker'!I3:I202,"Not Started") -> 0 | F44: =COUNTIFS('Task Tracker'!B3:B202,"Operations",'Task Tracker'!I3:I202,"Done") -> 0 | G44: =COUNTIF('Task Tracker'!B3:B202,"Operations") -> 0
A45: Legal | B45: =COUNTIFS('Task Tracker'!B3:B202,"Legal",'Task Tracker'!I3:I202,"Overdue") -> 0 | C45: =COUNTIFS('Task Tracker'!B3:B202,"Legal",'Task Tracker'!I3:I202,"In Progress") -> 0 | D45: =COUNTIFS('Task Tracker'!B3:B202,"Legal",'Task Tracker'!I3:I202,"Pending") -> 0 | E45: =COUNTIFS('Task Tracker'!B3:B202,"Legal",'Task Tracker'!I3:I202,"Not Started") -> 0 | F45: =COUNTIFS('Task Tracker'!B3:B202,"Legal",'Task Tracker'!I3:I202,"Done") -> 0 | G45: =COUNTIF('Task Tracker'!B3:B202,"Legal") -> 0
A46: Marketing | B46: =COUNTIFS('Task Tracker'!B3:B202,"Marketing",'Task Tracker'!I3:I202,"Overdue") -> 0 | C46: =COUNTIFS('Task Tracker'!B3:B202,"Marketing",'Task Tracker'!I3:I202,"In Progress") -> 0 | D46: =COUNTIFS('Task Tracker'!B3:B202,"Marketing",'Task Tracker'!I3:I202,"Pending") -> 0 | E46: =COUNTIFS('Task Tracker'!B3:B202,"Marketing",'Task Tracker'!I3:I202,"Not Started") -> 0 | F46: =COUNTIFS('Task Tracker'!B3:B202,"Marketing",'Task Tracker'!I3:I202,"Done") -> 0 | G46: =COUNTIF('Task Tracker'!B3:B202,"Marketing") -> 0

Sheet Today's Focus
A1: ="Today's Focus | "&TEXT(TODAY(),"DD MMM YYYY") -> Today's Focus | 05 Jun 2026
A2: Auto-populated — Overdue tasks + tasks due in the next 3 days (excludes Done). Open Task Tracker to update.
A3: # | B3: Department | C3: Task / Activity | D3: Assignee | E3: Client | F3: Priority | G3: Deadline | H3: Remarks | I3: Status | J3: Days Left
A4: =IFERROR(filter('Task Tracker'!B3:K202,(('Task Tracker'!I3:I202="Overdue")+(('Task Tracker'!J3:J202<=3)*('Task Tracker'!J3:J202>=0)*('Task Tracker'!I3:I202<>"Done")))*('Task Tracker'!C3:C202<>"")),"No urgent tasks — all clear!") -> No urgent tasks — all clear!

Sheet Task Tracker
A1: 88gravity | Delegation & Task Tracker v4
A2: # | B2: Department | C2: Task / Activity | D2: Assignee | E2: Client / Project | F2: Priority | G2: Deadline | H2: Remarks | I2: Status | J2: Days Left | K2: Added By
A3: =IF(C3="","",ROW()-2) -> 1 | B3: Client | C3: Follow up on MSA and SOW | D3: Adarsh | E3: Enout | F3: High | G3: 46177 | H3: Sent proposal, awaiting signed docs | I3: Pending | J3: =IF(C3="","",IF(I3="Done","Done",G3-TODAY())) -> -1 | K3: Adarsh
A4: =IF(C4="","",ROW()-2) -> 2 | B4: Client | C4: AI roadmap review — feedback pending | D4: Adarsh | E4: Enout | F4: High | G4: 46178 | H4: Shared on last call | I4: Pending | J4: =IF(C4="","",IF(I4="Done","Done",G4-TODAY())) -> 0 | K4: Adarsh
A5: =IF(C5="","",ROW()-2) -> 3 | B5: Client | C5: Doctor video interview script approval | D5: Priya | E5: Tiaraa Kerala | F5: High | G5: 46179 | H5: Script drafted, awaiting sign-off | I5: In Progress | J5: =IF(C5="","",IF(I5="Done","Done",G5-TODAY())) -> 1 | K5: Adarsh
A6: =IF(C6="","",ROW()-2) -> 4 | B6: Client | C6: ORM escalation — negative review spike | D6: Priya | E6: Colonelz | F6: High | G6: 46177 | H6: 5 new negative reviews this week | I6: Pending | J6: =IF(C6="","",IF(I6="Done","Done",G6-TODAY())) -> -1 | K6: Adarsh
A7: =IF(C7="","",ROW()-2) -> 5 | B7: Client | C7: Content calendar — Q3 plan | D7: Content Team | E7: Tiaraq Hotels | F7: Medium | G7: 46183 | H7: Q3 calendar due | I7: Not Started | J7: =IF(C7="","",IF(I7="Done","Done",G7-TODAY())) -> 5 | K7: Adarsh
A8: =IF(C8="","",ROW()-2) -> 6 | B8: Client | C8: Monthly SEO report deck | D8: SEO Team | E8: Chalk Studio | F8: High | G8: 46181 | H8: Data done, deck pending | I8: In Progress | J8: =IF(C8="","",IF(I8="Done","Done",G8-TODAY())) -> 3 | K8: Adarsh
A9: =IF(C9="","",ROW()-2) -> 7 | B9: Client | C9: Monthly report — PPC + SEO | D9: SEO Team | E9: Mobility Infotech | F9: High | G9: 46181 | H9: Combined report | I9: In Progress | J9: =IF(C9="","",IF(I9="Done","Done",G9-TODAY())) -> 3 | K9: Adarsh
A10: =IF(C10="","",ROW()-2) -> 8 | B10: Client | C10: Annual offsite approval | D10: Priya | E10: SKIL Events | F10: Low | G10: 46187 | H10: Budget approval pending | I10: Not Started | J10: =IF(C10="","",IF(I10="Done","Done",G10-TODAY())) -> 9 | K10: Adarsh
A11: =IF(C11="","",ROW()-2) -> 9 | B11: Finance | C11: Payment follow-up — Invoice #88G-041 | D11: Adarsh | E11: Colonelz | F11: High | G11: 46175 | H11: 30 days outstanding | I11: Overdue | J11: =IF(C11="","",IF(I11="Done","Done",G11-TODAY())) -> -3 | K11: Adarsh
A12: =IF(C12="","",ROW()-2) -> 10 | B12: Finance | C12: Invoice follow-up — Oct retainer | D12: Adarsh | E12: Catalyze | F12: High | G12: 46176 | H12: Second reminder needed | I12: Overdue | J12: =IF(C12="","",IF(I12="Done","Done",G12-TODAY())) -> -2 | K12: Adarsh
A13: =IF(C13="","",ROW()-2) -> 11 | B13: Sales | C13: Cost negotiation follow-up | D13: Adarsh | E13: Neon Cloud | F13: High | G13: 46178 | H13: Last quote sent 3 days ago | I13: Pending | J13: =IF(C13="","",IF(I13="Done","Done",G13-TODAY())) -> 0 | K13: Adarsh
A14: =IF(C14="","",ROW()-2) -> 12 | B14: Sales | C14: Proposal follow-up — HRMS Product | D14: Adarsh | E14: B2B Prospect | F14: Medium | G14: 46180 | H14: Deck shared last week | I14: Pending | J14: =IF(C14="","",IF(I14="Done","Done",G14-TODAY())) -> 2 | K14: Adarsh
... A22: =IF(C22="","",ROW()-2) -> 20 | B22: Team | C22: LinkedIn lead gen campaign — wk2 review | D22: Social Team | E22: Internal | F22: Medium | G22: 46182 | H22: Week 2 metrics due | I22: In Progress | J22: =IF(C22="","",IF(I22="Done","Done",G22-TODAY())) -> 4 | K22: Adarsh
A23: =IF(C23="","",ROW()-2) | J23: =IF(C23="","",IF(I23="Done","Done",G23-TODAY()))
A24: =IF(C24="","",ROW()-2) | J24: =IF(C24="","",IF(I24="Done","Done",G24-TODAY()))
A25: =IF(C25="","",ROW()-2) | J25: =IF(C25="","",IF(I25="Done","Done",G25-TODAY()))
A26: =IF(C26="","",ROW()-2) | J26: =IF(C26="","",IF(I26="Done","Done",G26-TODAY()))
A27: =IF(C27="","",ROW()-2) | J27: =IF(C27="","",IF(I27="Done","Done",G27-TODAY()))
A28: =IF(C28="","",ROW()-2) | J28: =IF(C28="","",IF(I28="Done","Done",G28-TODAY()))
A29: =IF(C29="","",ROW()-2) | J29: =IF(C29="","",IF(I29="Done","Done",G29-TODAY()))
A30: =IF(C30="","",ROW()-2) | J30: =IF(C30="","",IF(I30="Done","Done",G30-TODAY()))
A31: =IF(C31="","",ROW()-2) | J31: =IF(C31="","",IF(I31="Done","Done",G31-TODAY()))
A32: =IF(C32="","",ROW()-2) | J32: =IF(C32="","",IF(I32="Done","Done",G32-TODAY()))
A33: =IF(C33="","",ROW()-2) | J33: =IF(C33="","",IF(I33="Done","Done",G33-TODAY()))
A34: =IF(C34="","",ROW()-2) | J34: =IF(C34="","",IF(I34="Done","Done",G34-TODAY()))
... A202: =IF(C202="","",ROW()-2) | J202: =IF(C202="","",IF(I202="Done","Done",G202-TODAY()))

Sheet By Client
A1: 88gravity | View by Client / Project
A2: Select Client ▾ | C2: Enout | F2: ="Total: "&TEXT(COUNTIF('Task Tracker'!E3:E202,C2),"0") -> Total: 2 | G2: ="Overdue: "&TEXT(COUNTIFS('Task Tracker'!E3:E202,C2,'Task Tracker'!I3:I202,"Overdue"),"0") -> Overdue: 0 | H2: ="Pending: "&TEXT(COUNTIFS('Task Tracker'!E3:E202,C2,'Task Tracker'!I3:I202,"Pending"),"0") -> Pending: 2 | I2: ="In Prog: "&TEXT(COUNTIFS('Task Tracker'!E3:E202,C2,'Task Tracker'!I3:I202,"In Progress"),"0") -> In Prog: 0 | J2: ="Done: "&TEXT(COUNTIFS('Task Tracker'!E3:E202,C2,'Task Tracker'!I3:I202,"Done"),"0") -> Done: 0
A3: # | B3: Department | C3: Task / Activity | D3: Assignee | E3: Client | F3: Priority | G3: Deadline | H3: Remarks | I3: Status | J3: Days Left
A4: =IFERROR(filter('Task Tracker'!B3:K202,('Task Tracker'!E3:E202=C2)*('Task Tracker'!C3:C202<>"")),"No tasks found for this client") -> No tasks found for this client

Sheet By Assignee
A1: 88gravity | View by Assignee / Team Member
A2: Select Assignee ▾ | C2: Adarsh | F2: ="Total: "&TEXT(COUNTIF('Task Tracker'!D3:D202,C2),"0") -> Total: 6 | G2: ="Overdue: "&TEXT(COUNTIFS('Task Tracker'!D3:D202,C2,'Task Tracker'!I3:I202,"Overdue"),"0") -> Overdue: 2 | H2: ="Pending: "&TEXT(COUNTIFS('Task Tracker'!D3:D202,C2,'Task Tracker'!I3:I202,"Pending"),"0") -> Pending: 4 | I2: ="In Prog: "&TEXT(COUNTIFS('Task Tracker'!D3:D202,C2,'Task Tracker'!I3:I202,"In Progress"),"0") -> In Prog: 0 | J2: ="Done: "&TEXT(COUNTIFS('Task Tracker'!D3:D202,C2,'Task Tracker'!I3:I202,"Done"),"0") -> Done: 0
A3: # | B3: Department | C3: Task / Activity | D3: Assignee | E3: Client | F3: Priority | G3: Deadline | H3: Remarks | I3: Status | J3: Days Left
A4: =IFERROR(filter('Task Tracker'!B3:K202,('Task Tracker'!D3:D202=C2)*('Task Tracker'!C3:C202<>"")),"No tasks found for this assignee") -> No tasks found for this assignee

Sheet Settings
A1: Adarsh | B1: Enout | C1: Client | D1: High | E1: Pending | F1: Adarsh
A2: Kuldeep | B2: Tiaraa Kerala | C2: Finance | D2: Medium | E2: In Progress | F2: Kuldeep
A3: Priya | B3: Tiaraq Hotels | C3: Sales | D3: Low | E3: Not Started
A4: Rahul | B4: Colonelz | C4: HR | E4: Done
A5: SEO Team | B5: Chalk Studio | C5: Team | E5: Overdue
A6: Content Team | B6: Catalyze | C6: Operations
A7: Sales Team | B7: Mobility Infotech | C7: Legal
A8: Social Team | B8: SKIL Events | C8: Marketing
A9: Dev Team | B9: Neon Cloud
A10: HR Team | B10: B2B Prospect
B11: Prospect
B12: Internal
